{
  "n": 11,
  "count_total": 51,
  "count_survivors": 5,
  "records": [
    {
      "report": {
        "name": "C11_cyc_1_2_3_5",
        "n": 11,
        "family": "cyclic",
        "formula": "S_i = i + [1, 2, 3, 5] mod 11",
        "pair_cap_ok": true,
        "max_common": 2,
        "indegree_min": 4,
        "indegree_max": 4,
        "odd_cycle": true,
        "rectangle_trap": 0,
        "mutual_phi": 0,
        "forced_classes": [],
        "natural_vertex_circle_obstructed": null,
        "num_filters_passed": 2,
        "survives_all_exact_filters": false,
        "pattern_S": [
          [
            1,
            2,
            3,
            5
          ],
          [
            2,
            3,
            4,
            6
          ],
          [
            3,
            4,
            5,
            7
          ],
          [
            4,
            5,
            6,
            8
          ],
          [
            5,
            6,
            7,
            9
          ],
          [
            6,
            7,
            8,
            10
          ],
          [
            0,
            7,
            8,
            9
          ],
          [
            1,
            8,
            9,
            10
          ],
          [
            0,
            2,
            9,
            10
          ],
          [
            0,
            1,
            3,
            10
          ],
          [
            0,
            1,
            2,
            4
          ]
        ]
      },
      "numeric": null
    },
    {
      "report": {
        "name": "C11_cyc_1_2_3_6",
        "n": 11,
        "family": "cyclic",
        "formula": "S_i = i + [1, 2, 3, 6] mod 11",
        "pair_cap_ok": true,
        "max_common": 2,
        "indegree_min": 4,
        "indegree_max": 4,
        "odd_cycle": true,
        "rectangle_trap": 0,
        "mutual_phi": 0,
        "forced_classes": [],
        "natural_vertex_circle_obstructed": null,
        "num_filters_passed": 2,
        "survives_all_exact_filters": false,
        "pattern_S": [
          [
            1,
            2,
            3,
            6
          ],
          [
            2,
            3,
            4,
            7
          ],
          [
            3,
            4,
            5,
            8
          ],
          [
            4,
            5,
            6,
            9
          ],
          [
            5,
            6,
            7,
            10
          ],
          [
            0,
            6,
            7,
            8
          ],
          [
            1,
            7,
            8,
            9
          ],
          [
            2,
            8,
            9,
            10
          ],
          [
            0,
            3,
            9,
            10
          ],
          [
            0,
            1,
            4,
            10
          ],
          [
            0,
            1,
            2,
            5
          ]
        ]
      },
      "numeric": null
    },
    {
      "report": {
        "name": "C11_cyc_1_2_3_7",
        "n": 11,
        "family": "cyclic",
        "formula": "S_i = i + [1, 2, 3, 7] mod 11",
        "pair_cap_ok": true,
        "max_common": 2,
        "indegree_min": 4,
        "indegree_max": 4,
        "odd_cycle": true,
        "rectangle_trap": 0,
        "mutual_phi": 0,
        "forced_classes": [],
        "natural_vertex_circle_obstructed": null,
        "num_filters_passed": 2,
        "survives_all_exact_filters": false,
        "pattern_S": [
          [
            1,
            2,
            3,
            7
          ],
          [
            2,
            3,
            4,
            8
          ],
          [
            3,
            4,
            5,
            9
          ],
          [
            4,
            5,
            6,
            10
          ],
          [
            0,
            5,
            6,
            7
          ],
          [
            1,
            6,
            7,
            8
          ],
          [
            2,
            7,
            8,
            9
          ],
          [
            3,
            8,
            9,
            10
          ],
          [
            0,
            4,
            9,
            10
          ],
          [
            0,
            1,
            5,
            10
          ],
          [
            0,
            1,
            2,
            6
          ]
        ]
      },
      "numeric": null
    },
    {
      "report": {
        "name": "C11_cyc_1_2_4_5",
        "n": 11,
        "family": "cyclic",
        "formula": "S_i = i + [1, 2, 4, 5] mod 11",
        "pair_cap_ok": true,
        "max_common": 2,
        "indegree_min": 4,
        "indegree_max": 4,
        "odd_cycle": false,
        "rectangle_trap": 0,
        "mutual_phi": 0,
        "forced_classes": [],
        "natural_vertex_circle_obstructed": null,
        "num_filters_passed": 3,
        "survives_all_exact_filters": false,
        "pattern_S": [
          [
            1,
            2,
            4,
            5
          ],
          [
            2,
            3,
            5,
            6
          ],
          [
            3,
            4,
            6,
            7
          ],
          [
            4,
            5,
            7,
            8
          ],
          [
            5,
            6,
            8,
            9
          ],
          [
            6,
            7,
            9,
            10
          ],
          [
            0,
            7,
            8,
            10
          ],
          [
            0,
            1,
            8,
            9
          ],
          [
            1,
            2,
            9,
            10
          ],
          [
            0,
            2,
            3,
            10
          ],
          [
            0,
            1,
            3,
            4
          ]
        ]
      },
      "numeric": null
    },
    {
      "report": {
        "name": "C11_cyc_1_2_4_6",
        "n": 11,
        "family": "cyclic",
        "formula": "S_i = i + [1, 2, 4, 6] mod 11",
        "pair_cap_ok": true,
        "max_common": 2,
        "indegree_min": 4,
        "indegree_max": 4,
        "odd_cycle": true,
        "rectangle_trap": 0,
        "mutual_phi": 0,
        "forced_classes": [],
        "natural_vertex_circle_obstructed": null,
        "num_filters_passed": 3,
        "survives_all_exact_filters": false,
        "pattern_S": [
          [
            1,
            2,
            4,
            6
          ],
          [
            2,
            3,
            5,
            7
          ],
          [
            3,
            4,
            6,
            8
          ],
          [
            4,
            5,
            7,
            9
          ],
          [
            5,
            6,
            8,
            10
          ],
          [
            0,
            6,
            7,
            9
          ],
          [
            1,
            7,
            8,
            10
          ],
          [
            0,
            2,
            8,
            9
          ],
          [
            1,
            3,
            9,
            10
          ],
          [
            0,
            2,
            4,
            10
          ],
          [
            0,
            1,
            3,
            5
          ]
        ]
      },
      "numeric": null
    },
    {
      "report": {
        "name": "C11_cyc_1_2_4_7",
        "n": 11,
        "family": "cyclic",
        "formula": "S_i = i + [1, 2, 4, 7] mod 11",
        "pair_cap_ok": true,
        "max_common": 2,
        "indegree_min": 4,
        "indegree_max": 4,
        "odd_cycle": true,
        "rectangle_trap": 0,
        "mutual_phi": 0,
        "forced_classes": [],
        "natural_vertex_circle_obstructed": null,
        "num_filters_passed": 3,
        "survives_all_exact_filters": false,
        "pattern_S": [
          [
            1,
            2,
            4,
            7
          ],
          [
            2,
            3,
            5,
            8
          ],
          [
            3,
            4,
            6,
            9
          ],
          [
            4,
            5,
            7,
            10
          ],
          [
            0,
            5,
            6,
            8
          ],
          [
            1,
            6,
            7,
            9
          ],
          [
            2,
            7,
            8,
            10
          ],
          [
            0,
            3,
            8,
            9
          ],
          [
            1,
            4,
            9,
            10
          ],
          [
            0,
            2,
            5,
            10
          ],
          [
            0,
            1,
            3,
            6
          ]
        ]
      },
      "numeric": null
    },
    {
      "report": {
        "name": "C11_cyc_1_2_4_8",
        "n": 11,
        "family": "cyclic",
        "formula": "S_i = i + [1, 2, 4, 8] mod 11",
        "pair_cap_ok": true,
        "max_common": 2,
        "indegree_min": 4,
        "indegree_max": 4,
        "odd_cycle": true,
        "rectangle_trap": 0,
        "mutual_phi": 0,
        "forced_classes": [],
        "natural_vertex_circle_obstructed": null,
        "num_filters_passed": 3,
        "survives_all_exact_filters": false,
        "pattern_S": [
          [
            1,
            2,
            4,
            8
          ],
          [
            2,
            3,
            5,
            9
          ],
          [
            3,
            4,
            6,
            10
          ],
          [
            0,
            4,
            5,
            7
          ],
          [
            1,
            5,
            6,
            8
          ],
          [
            2,
            6,
            7,
            9
          ],
          [
            3,
            7,
            8,
            10
          ],
          [
            0,
            4,
            8,
            9
          ],
          [
            1,
            5,
            9,
            10
          ],
          [
            0,
            2,
            6,
            10
          ],
          [
            0,
            1,
            3,
            7
          ]
        ]
      },
      "numeric": null
    },
    {
      "report": {
        "name": "C11_cyc_1_2_4_9",
        "n": 11,
        "family": "cyclic",
        "formula": "S_i = i + [1, 2, 4, 9] mod 11",
        "pair_cap_ok": true,
        "max_common": 2,
        "indegree_min": 4,
        "indegree_max": 4,
        "odd_cycle": true,
        "rectangle_trap": 0,
        "mutual_phi": 0,
        "forced_classes": [],
        "natural_vertex_circle_obstructed": null,
        "num_filters_passed": 3,
        "survives_all_exact_filters": false,
        "pattern_S": [
          [
            1,
            2,
            4,
            9
          ],
          [
            2,
            3,
            5,
            10
          ],
          [
            0,
            3,
            4,
            6
          ],
          [
            1,
            4,
            5,
            7
          ],
          [
            2,
            5,
            6,
            8
          ],
          [
            3,
            6,
            7,
            9
          ],
          [
            4,
            7,
            8,
            10
          ],
          [
            0,
            5,
            8,
            9
          ],
          [
            1,
            6,
            9,
            10
          ],
          [
            0,
            2,
            7,
            10
          ],
          [
            0,
            1,
            3,
            8
          ]
        ]
      },
      "numeric": null
    },
    {
      "report": {
        "name": "C11_cyc_1_2_4_10",
        "n": 11,
        "family": "cyclic",
        "formula": "S_i = i + [1, 2, 4, 10] mod 11",
        "pair_cap_ok": true,
        "max_common": 2,
        "indegree_min": 4,
        "indegree_max": 4,
        "odd_cycle": false,
        "rectangle_trap": 0,
        "mutual_phi": 0,
        "forced_classes": [],
        "natural_vertex_circle_obstructed": null,
        "num_filters_passed": 4,
        "survives_all_exact_filters": true,
        "pattern_S": [
          [
            1,
            2,
            4,
            10
          ],
          [
            0,
            2,
            3,
            5
          ],
          [
            1,
            3,
            4,
            6
          ],
          [
            2,
            4,
            5,
            7
          ],
          [
            3,
            5,
            6,
            8
          ],
          [
            4,
            6,
            7,
            9
          ],
          [
            5,
            7,
            8,
            10
          ],
          [
            0,
            6,
            8,
            9
          ],
          [
            1,
            7,
            9,
            10
          ],
          [
            0,
            2,
            8,
            10
          ],
          [
            0,
            1,
            3,
            9
          ]
        ]
      },
      "numeric": {
        "loss": 43.80171704323978,
        "eq_rms": 0.9977442403564857,
        "max_spread": 4.084535856077885,
        "max_rel_spread": 3.7400956397716754,
        "convexity_margin": 9.999999982518437e-05,
        "min_edge_length": 0.015806284680467877,
        "min_pair_distance": 0.015806284680467877,
        "cluster_collapse": false,
        "x_best": [
          -0.8418510434210607,
          -1.825685079813673,
          1.9252726684166934,
          2.0912914944644254,
          2.0466719902501507,
          -0.08115218566143678,
          -3.16642026081832,
          -2.74606122116916,
          1.0180484516527961,
          0.9008192813856999,
          0.8977432170741492,
          -0.4487286423984933,
          -0.4745063892431423,
          -0.48519888678703704,
          0.13207695515158258,
          0.052098857173962766,
          -0.008479685894909047,
          0.18613973289908461,
          0.1963853369327111,
          0.2038975765331334,
          0.8086867238341041,
          -0.12785089288147627
        ],
        "coordinates": [
          [
            0.6132763101113129,
            5.214872838704939e-17
          ],
          [
            0.6448983636131927,
            0.0452928184786204
          ],
          [
            0.6550932085028269,
            0.06305742250631957
          ],
          [
            1.2280035034269516,
            1.071167368659886
          ],
          [
            -0.2877523242774354,
            1.412414964849397
          ],
          [
            -0.6262334449868252,
            0.05677956459448578
          ],
          [
            -0.6959293666291344,
            -0.2226518507627612
          ],
          [
            -0.6994167551227579,
            -0.23806861945449864
          ],
          [
            -0.6969082456066358,
            -0.2556539527589479
          ],
          [
            -0.5019336635554529,
            -1.582614440549465
          ],
          [
            0.3669024145239568,
            -0.3497232755630363
          ]
        ]
      }
    },
    {
      "report": {
        "name": "C11_cyc_1_2_5_6",
        "n": 11,
        "family": "cyclic",
        "formula": "S_i = i + [1, 2, 5, 6] mod 11",
        "pair_cap_ok": true,
        "max_common": 2,
        "indegree_min": 4,
        "indegree_max": 4,
        "odd_cycle": false,
        "rectangle_trap": 0,
        "mutual_phi": 0,
        "forced_classes": [],
        "natural_vertex_circle_obstructed": null,
        "num_filters_passed": 3,
        "survives_all_exact_filters": false,
        "pattern_S": [
          [
            1,
            2,
            5,
            6
          ],
          [
            2,
            3,
            6,
            7
          ],
          [
            3,
            4,
            7,
            8
          ],
          [
            4,
            5,
            8,
            9
          ],
          [
            5,
            6,
            9,
            10
          ],
          [
            0,
            6,
            7,
            10
          ],
          [
            0,
            1,
            7,
            8
          ],
          [
            1,
            2,
            8,
            9
          ],
          [
            2,
            3,
            9,
            10
          ],
          [
            0,
            3,
            4,
            10
          ],
          [
            0,
            1,
            4,
            5
          ]
        ]
      },
      "numeric": null
    },
    {
      "report": {
        "name": "C11_cyc_1_2_5_7",
        "n": 11,
        "family": "cyclic",
        "formula": "S_i = i + [1, 2, 5, 7] mod 11",
        "pair_cap_ok": true,
        "max_common": 2,
        "indegree_min": 4,
        "indegree_max": 4,
        "odd_cycle": true,
        "rectangle_trap": 0,
        "mutual_phi": 0,
        "forced_classes": [],
        "natural_vertex_circle_obstructed": null,
        "num_filters_passed": 3,
        "survives_all_exact_filters": false,
        "pattern_S": [
          [
            1,
            2,
            5,
            7
          ],
          [
            2,
            3,
            6,
            8
          ],
          [
            3,
            4,
            7,
            9
          ],
          [
            4,
            5,
            8,
            10
          ],
          [
            0,
            5,
            6,
            9
          ],
          [
            1,
            6,
            7,
            10
          ],
          [
            0,
            2,
            7,
            8
          ],
          [
            1,
            3,
            8,
            9
          ],
          [
            2,
            4,
            9,
            10
          ],
          [
            0,
            3,
            5,
            10
          ],
          [
            0,
            1,
            4,
            6
          ]
        ]
      },
      "numeric": null
    },
    {
      "report": {
        "name": "C11_cyc_1_2_5_8",
        "n": 11,
        "family": "cyclic",
        "formula": "S_i = i + [1, 2, 5, 8] mod 11",
        "pair_cap_ok": true,
        "max_common": 2,
        "indegree_min": 4,
        "indegree_max": 4,
        "odd_cycle": true,
        "rectangle_trap": 0,
        "mutual_phi": 0,
        "forced_classes": [],
        "natural_vertex_circle_obstructed": null,
        "num_filters_passed": 3,
        "survives_all_exact_filters": false,
        "pattern_S": [
          [
            1,
            2,
            5,
            8
          ],
          [
            2,
            3,
            6,
            9
          ],
          [
            3,
            4,
            7,
            10
          ],
          [
            0,
            4,
            5,
            8
          ],
          [
            1,
            5,
            6,
            9
          ],
          [
            2,
            6,
            7,
            10
          ],
          [
            0,
            3,
            7,
            8
          ],
          [
            1,
            4,
            8,
            9
          ],
          [
            2,
            5,
            9,
            10
          ],
          [
            0,
            3,
            6,
            10
          ],
          [
            0,
            1,
            4,
            7
          ]
        ]
      },
      "numeric": null
    },
    {
      "report": {
        "name": "C11_cyc_1_2_6_8",
        "n": 11,
        "family": "cyclic",
        "formula": "S_i = i + [1, 2, 6, 8] mod 11",
        "pair_cap_ok": true,
        "max_common": 2,
        "indegree_min": 4,
        "indegree_max": 4,
        "odd_cycle": false,
        "rectangle_trap": 0,
        "mutual_phi": 0,
        "forced_classes": [],
        "natural_vertex_circle_obstructed": null,
        "num_filters_passed": 4,
        "survives_all_exact_filters": true,
        "pattern_S": [
          [
            1,
            2,
            6,
            8
          ],
          [
            2,
            3,
            7,
            9
          ],
          [
            3,
            4,
            8,
            10
          ],
          [
            0,
            4,
            5,
            9
          ],
          [
            1,
            5,
            6,
            10
          ],
          [
            0,
            2,
            6,
            7
          ],
          [
            1,
            3,
            7,
            8
          ],
          [
            2,
            4,
            8,
            9
          ],
          [
            3,
            5,
            9,
            10
          ],
          [
            0,
            4,
            6,
            10
          ],
          [
            0,
            1,
            5,
            7
          ]
        ]
      },
      "numeric": {
        "loss": 57.42282844401265,
        "eq_rms": 1.1423941013584014,
        "max_spread": 3.536090758154787,
        "max_rel_spread": 3.1548875262504996,
        "convexity_margin": 9.999999952965688e-05,
        "min_edge_length": 0.00032783025529481105,
        "min_pair_distance": 0.00032783025529481105,
        "cluster_collapse": false,
        "x_best": [
          -6.4508119551809955,
          2.178154910078279,
          3.209719676801702,
          -1.2915048729479865,
          0.44638588355946196,
          0.5415160010638042,
          -0.19231107061814207,
          0.857653085340519,
          -1.9624676775437406,
          2.054218441422837,
          0.8260672689965196,
          1.7261191826478204,
          1.7260604279649663,
          1.8292582830596555,
          -3.0945300366002035,
          -2.3878948154851147,
          -1.9236271905251126,
          -1.3916145420586128,
          -1.126987996721045,
          1.1445131386229255,
          1.891796391250341,
          1.6365520034845187
        ],
        "coordinates": [
          [
            1.0457164265849568,
            -6.848787360915662e-18
          ],
          [
            1.045670255311878,
            0.00032456261311022484
          ],
          [
            0.4986710404073066,
            1.6796261627026405
          ],
          [
            -0.5450956441945107,
            0.22876115747193934
          ],
          [
            -0.5527985689532707,
            0.21795806887295607
          ],
          [
            -0.5553301918763054,
            0.20142547239501415
          ],
          [
            -0.5540910392468285,
            0.17001732354365334
          ],
          [
            -0.5500139732326775,
            0.14737838820877686
          ],
          [
            -0.4027447488741458,
            -0.6458436091425973
          ],
          [
            -0.22108672433986418,
            -1.623611650518539
          ],
          [
            0.7911031684134611,
            -0.3760358761469539
          ]
        ]
      }
    },
    {
      "report": {
        "name": "A11_ac_1_3_4_5_r6_3_4_8_10",
        "n": 11,
        "family": "almost-cyclic",
        "formula": "cyclic((1, 3, 4, 5)) with row 6 -> [3, 4, 8, 10] mod 11",
        "pair_cap_ok": true,
        "max_common": 2,
        "indegree_min": 3,
        "indegree_max": 5,
        "odd_cycle": false,
        "rectangle_trap": 0,
        "mutual_phi": 0,
        "forced_classes": [],
        "natural_vertex_circle_obstructed": null,
        "num_filters_passed": 3,
        "survives_all_exact_filters": false,
        "pattern_S": [
          [
            1,
            3,
            4,
            5
          ],
          [
            2,
            4,
            5,
            6
          ],
          [
            3,
            5,
            6,
            7
          ],
          [
            4,
            6,
            7,
            8
          ],
          [
            5,
            7,
            8,
            9
          ],
          [
            6,
            8,
            9,
            10
          ],
          [
            3,
            5,
            9,
            10
          ],
          [
            0,
            1,
            8,
            10
          ],
          [
            0,
            1,
            2,
            9
          ],
          [
            1,
            2,
            3,
            10
          ],
          [
            0,
            2,
            3,
            4
          ]
        ]
      },
      "numeric": null
    },
    {
      "report": {
        "name": "A11_ac_1_3_4_5_r6_1_3_7_9",
        "n": 11,
        "family": "almost-cyclic",
        "formula": "cyclic((1, 3, 4, 5)) with row 6 -> [1, 3, 7, 9] mod 11",
        "pair_cap_ok": true,
        "max_common": 2,
        "indegree_min": 3,
        "indegree_max": 5,
        "odd_cycle": false,
        "rectangle_trap": 0,
        "mutual_phi": 0,
        "forced_classes": [],
        "natural_vertex_circle_obstructed": null,
        "num_filters_passed": 3,
        "survives_all_exact_filters": false,
        "pattern_S": [
          [
            1,
            3,
            4,
            5
          ],
          [
            2,
            4,
            5,
            6
          ],
          [
            3,
            5,
            6,
            7
          ],
          [
            4,
            6,
            7,
            8
          ],
          [
            5,
            7,
            8,
            9
          ],
          [
            6,
            8,
            9,
            10
          ],
          [
            2,
            4,
            7,
            9
          ],
          [
            0,
            1,
            8,
            10
          ],
          [
            0,
            1,
            2,
            9
          ],
          [
            1,
            2,
            3,
            10
          ],
          [
            0,
            2,
            3,
            4
          ]
        ]
      },
      "numeric": null
    },
    {
      "report": {
        "name": "A11_ac_1_3_4_5_r3_2_4_7_10",
        "n": 11,
        "family": "almost-cyclic",
        "formula": "cyclic((1, 3, 4, 5)) with row 3 -> [2, 4, 7, 10] mod 11",
        "pair_cap_ok": true,
        "max_common": 2,
        "indegree_min": 3,
        "indegree_max": 5,
        "odd_cycle": false,
        "rectangle_trap": 0,
        "mutual_phi": 0,
        "forced_classes": [],
        "natural_vertex_circle_obstructed": null,
        "num_filters_passed": 3,
        "survives_all_exact_filters": false,
        "pattern_S": [
          [
            1,
            3,
            4,
            5
          ],
          [
            2,
            4,
            5,
            6
          ],
          [
            3,
            5,
            6,
            7
          ],
          [
            2,
            5,
            7,
            10
          ],
          [
            5,
            7,
            8,
            9
          ],
          [
            6,
            8,
            9,
            10
          ],
          [
            0,
            7,
            9,
            10
          ],
          [
            0,
            1,
            8,
            10
          ],
          [
            0,
            1,
            2,
            9
          ],
          [
            1,
            2,
            3,
            10
          ],
          [
            0,
            2,
            3,
            4
          ]
        ]
      },
      "numeric": null
    },
    {
      "report": {
        "name": "A11_ac_1_3_4_5_r1_1_3_4_8",
        "n": 11,
        "family": "almost-cyclic",
        "formula": "cyclic((1, 3, 4, 5)) with row 1 -> [1, 3, 4, 8] mod 11",
        "pair_cap_ok": true,
        "max_common": 2,
        "indegree_min": 3,
        "indegree_max": 5,
        "odd_cycle": false,
        "rectangle_trap": 0,
        "mutual_phi": 0,
        "forced_classes": [],
        "natural_vertex_circle_obstructed": null,
        "num_filters_passed": 3,
        "survives_all_exact_filters": false,
        "pattern_S": [
          [
            1,
            3,
            4,
            5
          ],
          [
            2,
            4,
            5,
            9
          ],
          [
            3,
            5,
            6,
            7
          ],
          [
            4,
            6,
            7,
            8
          ],
          [
            5,
            7,
            8,
            9
          ],
          [
            6,
            8,
            9,
            10
          ],
          [
            0,
            7,
            9,
            10
          ],
          [
            0,
            1,
            8,
            10
          ],
          [
            0,
            1,
            2,
            9
          ],
          [
            1,
            2,
            3,
            10
          ],
          [
            0,
            2,
            3,
            4
          ]
        ]
      },
      "numeric": null
    },
    {
      "report": {
        "name": "A11_ac_1_3_4_5_r6_2_6_7_10",
        "n": 11,
        "family": "almost-cyclic",
        "formula": "cyclic((1, 3, 4, 5)) with row 6 -> [2, 6, 7, 10] mod 11",
        "pair_cap_ok": true,
        "max_common": 2,
        "indegree_min": 3,
        "indegree_max": 5,
        "odd_cycle": false,
        "rectangle_trap": 0,
        "mutual_phi": 0,
        "forced_classes": [],
        "natural_vertex_circle_obstructed": null,
        "num_filters_passed": 3,
        "survives_all_exact_filters": false,
        "pattern_S": [
          [
            1,
            3,
            4,
            5
          ],
          [
            2,
            4,
            5,
            6
          ],
          [
            3,
            5,
            6,
            7
          ],
          [
            4,
            6,
            7,
            8
          ],
          [
            5,
            7,
            8,
            9
          ],
          [
            6,
            8,
            9,
            10
          ],
          [
            1,
            2,
            5,
            8
          ],
          [
            0,
            1,
            8,
            10
          ],
          [
            0,
            1,
            2,
            9
          ],
          [
            1,
            2,
            3,
            10
          ],
          [
            0,
            2,
            3,
            4
          ]
        ]
      },
      "numeric": null
    },
    {
      "report": {
        "name": "A11_ac_1_3_4_5_r3_1_2_5_7",
        "n": 11,
        "family": "almost-cyclic",
        "formula": "cyclic((1, 3, 4, 5)) with row 3 -> [1, 2, 5, 7] mod 11",
        "pair_cap_ok": true,
        "max_common": 2,
        "indegree_min": 3,
        "indegree_max": 5,
        "odd_cycle": true,
        "rectangle_trap": 0,
        "mutual_phi": 0,
        "forced_classes": [],
        "natural_vertex_circle_obstructed": null,
        "num_filters_passed": 2,
        "survives_all_exact_filters": false,
        "pattern_S": [
          [
            1,
            3,
            4,
            5
          ],
          [
            2,
            4,
            5,
            6
          ],
          [
            3,
            5,
            6,
            7
          ],
          [
            4,
            5,
            8,
            10
          ],
          [
            5,
            7,
            8,
            9
          ],
          [
            6,
            8,
            9,
            10
          ],
          [
            0,
            7,
            9,
            10
          ],
          [
            0,
            1,
            8,
            10
          ],
          [
            0,
            1,
            2,
            9
          ],
          [
            1,
            2,
            3,
            10
          ],
          [
            0,
            2,
            3,
            4
          ]
        ]
      },
      "numeric": null
    },
    {
      "report": {
        "name": "A11_ac_1_3_4_5_r10_2_5_8_10",
        "n": 11,
        "family": "almost-cyclic",
        "formula": "cyclic((1, 3, 4, 5)) with row 10 -> [2, 5, 8, 10] mod 11",
        "pair_cap_ok": true,
        "max_common": 2,
        "indegree_min": 3,
        "indegree_max": 5,
        "odd_cycle": false,
        "rectangle_trap": 0,
        "mutual_phi": 0,
        "forced_classes": [],
        "natural_vertex_circle_obstructed": null,
        "num_filters_passed": 3,
        "survives_all_exact_filters": false,
        "pattern_S": [
          [
            1,
            3,
            4,
            5
          ],
          [
            2,
            4,
            5,
            6
          ],
          [
            3,
            5,
            6,
            7
          ],
          [
            4,
            6,
            7,
            8
          ],
          [
            5,
            7,
            8,
            9
          ],
          [
            6,
            8,
            9,
            10
          ],
          [
            0,
            7,
            9,
            10
          ],
          [
            0,
            1,
            8,
            10
          ],
          [
            0,
            1,
            2,
            9
          ],
          [
            1,
            2,
            3,
            10
          ],
          [
            1,
            4,
            7,
            9
          ]
        ]
      },
      "numeric": null
    },
    {
      "report": {
        "name": "A11_ac_1_3_4_5_r6_1_2_4_7",
        "n": 11,
        "family": "almost-cyclic",
        "formula": "cyclic((1, 3, 4, 5)) with row 6 -> [1, 2, 4, 7] mod 11",
        "pair_cap_ok": true,
        "max_common": 2,
        "indegree_min": 3,
        "indegree_max": 5,
        "odd_cycle": false,
        "rectangle_trap": 0,
        "mutual_phi": 0,
        "forced_classes": [],
        "natural_vertex_circle_obstructed": null,
        "num_filters_passed": 3,
        "survives_all_exact_filters": false,
        "pattern_S": [
          [
            1,
            3,
            4,
            5
          ],
          [
            2,
            4,
            5,
            6
          ],
          [
            3,
            5,
            6,
            7
          ],
          [
            4,
            6,
            7,
            8
          ],
          [
            5,
            7,
            8,
            9
          ],
          [
            6,
            8,
            9,
            10
          ],
          [
            2,
            7,
            8,
            10
          ],
          [
            0,
            1,
            8,
            10
          ],
          [
            0,
            1,
            2,
            9
          ],
          [
            1,
            2,
            3,
            10
          ],
          [
            0,
            2,
            3,
            4
          ]
        ]
      },
      "numeric": null
    },
    {
      "report": {
        "name": "A11_ac_1_3_4_5_r10_1_3_6_8",
        "n": 11,
        "family": "almost-cyclic",
        "formula": "cyclic((1, 3, 4, 5)) with row 10 -> [1, 3, 6, 8] mod 11",
        "pair_cap_ok": true,
        "max_common": 2,
        "indegree_min": 3,
        "indegree_max": 5,
        "odd_cycle": false,
        "rectangle_trap": 0,
        "mutual_phi": 0,
        "forced_classes": [],
        "natural_vertex_circle_obstructed": null,
        "num_filters_passed": 3,
        "survives_all_exact_filters": false,
        "pattern_S": [
          [
            1,
            3,
            4,
            5
          ],
          [
            2,
            4,
            5,
            6
          ],
          [
            3,
            5,
            6,
            7
          ],
          [
            4,
            6,
            7,
            8
          ],
          [
            5,
            7,
            8,
            9
          ],
          [
            6,
            8,
            9,
            10
          ],
          [
            0,
            7,
            9,
            10
          ],
          [
            0,
            1,
            8,
            10
          ],
          [
            0,
            1,
            2,
            9
          ],
          [
            1,
            2,
            3,
            10
          ],
          [
            0,
            2,
            5,
            7
          ]
        ]
      },
      "numeric": null
    },
    {
      "report": {
        "name": "A11_ac_1_3_4_5_r5_1_4_6_9",
        "n": 11,
        "family": "almost-cyclic",
        "formula": "cyclic((1, 3, 4, 5)) with row 5 -> [1, 4, 6, 9] mod 11",
        "pair_cap_ok": true,
        "max_common": 2,
        "indegree_min": 3,
        "indegree_max": 5,
        "odd_cycle": false,
        "rectangle_trap": 0,
        "mutual_phi": 0,
        "forced_classes": [],
        "natural_vertex_circle_obstructed": null,
        "num_filters_passed": 3,
        "survives_all_exact_filters": false,
        "pattern_S": [
          [
            1,
            3,
            4,
            5
          ],
          [
            2,
            4,
            5,
            6
          ],
          [
            3,
            5,
            6,
            7
          ],
          [
            4,
            6,
            7,
            8
          ],
          [
            5,
            7,
            8,
            9
          ],
          [
            0,
            3,
            6,
            9
          ],
          [
            0,
            7,
            9,
            10
          ],
          [
            0,
            1,
            8,
            10
          ],
          [
            0,
            1,
            2,
            9
          ],
          [
            1,
            2,
            3,
            10
          ],
          [
            0,
            2,
            3,
            4
          ]
        ]
      },
      "numeric": null
    },
    {
      "report": {
        "name": "A11_ac_1_3_4_5_r7_3_7_8_10",
        "n": 11,
        "family": "almost-cyclic",
        "formula": "cyclic((1, 3, 4, 5)) with row 7 -> [3, 7, 8, 10] mod 11",
        "pair_cap_ok": true,
        "max_common": 2,
        "indegree_min": 3,
        "indegree_max": 5,
        "odd_cycle": false,
        "rectangle_trap": 0,
        "mutual_phi": 0,
        "forced_classes": [],
        "natural_vertex_circle_obstructed": null,
        "num_filters_passed": 3,
        "survives_all_exact_filters": false,
        "pattern_S": [
          [
            1,
            3,
            4,
            5
          ],
          [
            2,
            4,
            5,
            6
          ],
          [
            3,
            5,
            6,
            7
          ],
          [
            4,
            6,
            7,
            8
          ],
          [
            5,
            7,
            8,
            9
          ],
          [
            6,
            8,
            9,
            10
          ],
          [
            0,
            7,
            9,
            10
          ],
          [
            3,
            4,
            6,
            10
          ],
          [
            0,
            1,
            2,
            9
          ],
          [
            1,
            2,
            3,
            10
          ],
          [
            0,
            2,
            3,
            4
          ]
        ]
      },
      "numeric": null
    },
    {
      "report": {
        "name": "A11_ac_1_3_4_5_r5_1_6_7_10",
        "n": 11,
        "family": "almost-cyclic",
        "formula": "cyclic((1, 3, 4, 5)) with row 5 -> [1, 6, 7, 10] mod 11",
        "pair_cap_ok": true,
        "max_common": 2,
        "indegree_min": 3,
        "indegree_max": 5,
        "odd_cycle": false,
        "rectangle_trap": 0,
        "mutual_phi": 0,
        "forced_classes": [],
        "natural_vertex_circle_obstructed": null,
        "num_filters_passed": 3,
        "survives_all_exact_filters": false,
        "pattern_S": [
          [
            1,
            3,
            4,
            5
          ],
          [
            2,
            4,
            5,
            6
          ],
          [
            3,
            5,
            6,
            7
          ],
          [
            4,
            6,
            7,
            8
          ],
          [
            5,
            7,
            8,
            9
          ],
          [
            0,
            1,
            4,
            6
          ],
          [
            0,
            7,
            9,
            10
          ],
          [
            0,
            1,
            8,
            10
          ],
          [
            0,
            1,
            2,
            9
          ],
          [
            1,
            2,
            3,
            10
          ],
          [
            0,
            2,
            3,
            4
          ]
        ]
      },
      "numeric": null
    },
    {
      "report": {
        "name": "A11_ac_1_3_4_5_r4_1_5_6_9",
        "n": 11,
        "family": "almost-cyclic",
        "formula": "cyclic((1, 3, 4, 5)) with row 4 -> [1, 5, 6, 9] mod 11",
        "pair_cap_ok": true,
        "max_common": 2,
        "indegree_min": 3,
        "indegree_max": 5,
        "odd_cycle": false,
        "rectangle_trap": 0,
        "mutual_phi": 0,
        "forced_classes": [],
        "natural_vertex_circle_obstructed": null,
        "num_filters_passed": 3,
        "survives_all_exact_filters": false,
        "pattern_S": [
          [
            1,
            3,
            4,
            5
          ],
          [
            2,
            4,
            5,
            6
          ],
          [
            3,
            5,
            6,
            7
          ],
          [
            4,
            6,
            7,
            8
          ],
          [
            2,
            5,
            9,
            10
          ],
          [
            6,
            8,
            9,
            10
          ],
          [
            0,
            7,
            9,
            10
          ],
          [
            0,
            1,
            8,
            10
          ],
          [
            0,
            1,
            2,
            9
          ],
          [
            1,
            2,
            3,
            10
          ],
          [
            0,
            2,
            3,
            4
          ]
        ]
      },
      "numeric": null
    },
    {
      "report": {
        "name": "A11_ac_1_3_4_5_r2_2_3_8_9",
        "n": 11,
        "family": "almost-cyclic",
        "formula": "cyclic((1, 3, 4, 5)) with row 2 -> [2, 3, 8, 9] mod 11",
        "pair_cap_ok": true,
        "max_common": 2,
        "indegree_min": 3,
        "indegree_max": 5,
        "odd_cycle": true,
        "rectangle_trap": 0,
        "mutual_phi": 0,
        "forced_classes": [],
        "natural_vertex_circle_obstructed": null,
        "num_filters_passed": 2,
        "survives_all_exact_filters": false,
        "pattern_S": [
          [
            1,
            3,
            4,
            5
          ],
          [
            2,
            4,
            5,
            6
          ],
          [
            0,
            4,
            5,
            10
          ],
          [
            4,
            6,
            7,
            8
          ],
          [
            5,
            7,
            8,
            9
          ],
          [
            6,
            8,
            9,
            10
          ],
          [
            0,
            7,
            9,
            10
          ],
          [
            0,
            1,
            8,
            10
          ],
          [
            0,
            1,
            2,
            9
          ],
          [
            1,
            2,
            3,
            10
          ],
          [
            0,
            2,
            3,
            4
          ]
        ]
      },
      "numeric": null
    },
    {
      "report": {
        "name": "A11_ac_1_3_4_5_r4_2_5_9_10",
        "n": 11,
        "family": "almost-cyclic",
        "formula": "cyclic((1, 3, 4, 5)) with row 4 -> [2, 5, 9, 10] mod 11",
        "pair_cap_ok": true,
        "max_common": 2,
        "indegree_min": 3,
        "indegree_max": 5,
        "odd_cycle": false,
        "rectangle_trap": 0,
        "mutual_phi": 0,
        "forced_classes": [],
        "natural_vertex_circle_obstructed": null,
        "num_filters_passed": 3,
        "survives_all_exact_filters": false,
        "pattern_S": [
          [
            1,
            3,
            4,
            5
          ],
          [
            2,
            4,
            5,
            6
          ],
          [
            3,
            5,
            6,
            7
          ],
          [
            4,
            6,
            7,
            8
          ],
          [
            2,
            3,
            6,
            9
          ],
          [
            6,
            8,
            9,
            10
          ],
          [
            0,
            7,
            9,
            10
          ],
          [
            0,
            1,
            8,
            10
          ],
          [
            0,
            1,
            2,
            9
          ],
          [
            1,
            2,
            3,
            10
          ],
          [
            0,
            2,
            3,
            4
          ]
        ]
      },
      "numeric": null
    },
    {
      "report": {
        "name": "A11_ac_1_3_4_5_r1_3_4_5_10",
        "n": 11,
        "family": "almost-cyclic",
        "formula": "cyclic((1, 3, 4, 5)) with row 1 -> [3, 4, 5, 10] mod 11",
        "pair_cap_ok": true,
        "max_common": 2,
        "indegree_min": 3,
        "indegree_max": 5,
        "odd_cycle": true,
        "rectangle_trap": 0,
        "mutual_phi": 0,
        "forced_classes": [],
        "natural_vertex_circle_obstructed": null,
        "num_filters_passed": 2,
        "survives_all_exact_filters": false,
        "pattern_S": [
          [
            1,
            3,
            4,
            5
          ],
          [
            0,
            4,
            5,
            6
          ],
          [
            3,
            5,
            6,
            7
          ],
          [
            4,
            6,
            7,
            8
          ],
          [
            5,
            7,
            8,
            9
          ],
          [
            6,
            8,
            9,
            10
          ],
          [
            0,
            7,
            9,
            10
          ],
          [
            0,
            1,
            8,
            10
          ],
          [
            0,
            1,
            2,
            9
          ],
          [
            1,
            2,
            3,
            10
          ],
          [
            0,
            2,
            3,
            4
          ]
        ]
      },
      "numeric": null
    },
    {
      "report": {
        "name": "A11_ac_1_3_4_5_r0_1_4_5_8",
        "n": 11,
        "family": "almost-cyclic",
        "formula": "cyclic((1, 3, 4, 5)) with row 0 -> [1, 4, 5, 8] mod 11",
        "pair_cap_ok": true,
        "max_common": 2,
        "indegree_min": 3,
        "indegree_max": 5,
        "odd_cycle": false,
        "rectangle_trap": 0,
        "mutual_phi": 0,
        "forced_classes": [],
        "natural_vertex_circle_obstructed": null,
        "num_filters_passed": 3,
        "survives_all_exact_filters": false,
        "pattern_S": [
          [
            1,
            4,
            5,
            8
          ],
          [
            2,
            4,
            5,
            6
          ],
          [
            3,
            5,
            6,
            7
          ],
          [
            4,
            6,
            7,
            8
          ],
          [
            5,
            7,
            8,
            9
          ],
          [
            6,
            8,
            9,
            10
          ],
          [
            0,
            7,
            9,
            10
          ],
          [
            0,
            1,
            8,
            10
          ],
          [
            0,
            1,
            2,
            9
          ],
          [
            1,
            2,
            3,
            10
          ],
          [
            0,
            2,
            3,
            4
          ]
        ]
      },
      "numeric": null
    },
    {
      "report": {
        "name": "A11_ac_1_3_4_5_r4_2_5_7_10",
        "n": 11,
        "family": "almost-cyclic",
        "formula": "cyclic((1, 3, 4, 5)) with row 4 -> [2, 5, 7, 10] mod 11",
        "pair_cap_ok": true,
        "max_common": 2,
        "indegree_min": 3,
        "indegree_max": 5,
        "odd_cycle": true,
        "rectangle_trap": 0,
        "mutual_phi": 0,
        "forced_classes": [],
        "natural_vertex_circle_obstructed": null,
        "num_filters_passed": 2,
        "survives_all_exact_filters": false,
        "pattern_S": [
          [
            1,
            3,
            4,
            5
          ],
          [
            2,
            4,
            5,
            6
          ],
          [
            3,
            5,
            6,
            7
          ],
          [
            4,
            6,
            7,
            8
          ],
          [
            0,
            3,
            6,
            9
          ],
          [
            6,
            8,
            9,
            10
          ],
          [
            0,
            7,
            9,
            10
          ],
          [
            0,
            1,
            8,
            10
          ],
          [
            0,
            1,
            2,
            9
          ],
          [
            1,
            2,
            3,
            10
          ],
          [
            0,
            2,
            3,
            4
          ]
        ]
      },
      "numeric": null
    },
    {
      "report": {
        "name": "A11_ac_2_3_5_8_r10_3_4_5_8",
        "n": 11,
        "family": "almost-cyclic",
        "formula": "cyclic((2, 3, 5, 8)) with row 10 -> [3, 4, 5, 8] mod 11",
        "pair_cap_ok": true,
        "max_common": 2,
        "indegree_min": 3,
        "indegree_max": 5,
        "odd_cycle": false,
        "rectangle_trap": 0,
        "mutual_phi": 0,
        "forced_classes": [],
        "natural_vertex_circle_obstructed": null,
        "num_filters_passed": 3,
        "survives_all_exact_filters": false,
        "pattern_S": [
          [
            2,
            3,
            5,
            8
          ],
          [
            3,
            4,
            6,
            9
          ],
          [
            4,
            5,
            7,
            10
          ],
          [
            0,
            5,
            6,
            8
          ],
          [
            1,
            6,
            7,
            9
          ],
          [
            2,
            7,
            8,
            10
          ],
          [
            0,
            3,
            8,
            9
          ],
          [
            1,
            4,
            9,
            10
          ],
          [
            0,
            2,
            5,
            10
          ],
          [
            0,
            1,
            3,
            6
          ],
          [
            2,
            3,
            4,
            7
          ]
        ]
      },
      "numeric": null
    },
    {
      "report": {
        "name": "A11_ac_2_3_5_8_r3_1_3_7_10",
        "n": 11,
        "family": "almost-cyclic",
        "formula": "cyclic((2, 3, 5, 8)) with row 3 -> [1, 3, 7, 10] mod 11",
        "pair_cap_ok": true,
        "max_common": 2,
        "indegree_min": 3,
        "indegree_max": 5,
        "odd_cycle": false,
        "rectangle_trap": 0,
        "mutual_phi": 0,
        "forced_classes": [],
        "natural_vertex_circle_obstructed": null,
        "num_filters_passed": 3,
        "survives_all_exact_filters": false,
        "pattern_S": [
          [
            2,
            3,
            5,
            8
          ],
          [
            3,
            4,
            6,
            9
          ],
          [
            4,
            5,
            7,
            10
          ],
          [
            2,
            4,
            6,
            10
          ],
          [
            1,
            6,
            7,
            9
          ],
          [
            2,
            7,
            8,
            10
          ],
          [
            0,
            3,
            8,
            9
          ],
          [
            1,
            4,
            9,
            10
          ],
          [
            0,
            2,
            5,
            10
          ],
          [
            0,
            1,
            3,
            6
          ],
          [
            1,
            2,
            4,
            7
          ]
        ]
      },
      "numeric": null
    },
    {
      "report": {
        "name": "A11_ac_2_3_5_8_r4_1_2_5_8",
        "n": 11,
        "family": "almost-cyclic",
        "formula": "cyclic((2, 3, 5, 8)) with row 4 -> [1, 2, 5, 8] mod 11",
        "pair_cap_ok": true,
        "max_common": 2,
        "indegree_min": 3,
        "indegree_max": 5,
        "odd_cycle": true,
        "rectangle_trap": 0,
        "mutual_phi": 0,
        "forced_classes": [],
        "natural_vertex_circle_obstructed": null,
        "num_filters_passed": 2,
        "survives_all_exact_filters": false,
        "pattern_S": [
          [
            2,
            3,
            5,
            8
          ],
          [
            3,
            4,
            6,
            9
          ],
          [
            4,
            5,
            7,
            10
          ],
          [
            0,
            5,
            6,
            8
          ],
          [
            1,
            5,
            6,
            9
          ],
          [
            2,
            7,
            8,
            10
          ],
          [
            0,
            3,
            8,
            9
          ],
          [
            1,
            4,
            9,
            10
          ],
          [
            0,
            2,
            5,
            10
          ],
          [
            0,
            1,
            3,
            6
          ],
          [
            1,
            2,
            4,
            7
          ]
        ]
      },
      "numeric": null
    },
    {
      "report": {
        "name": "A11_ac_2_3_5_8_r3_1_3_8_10",
        "n": 11,
        "family": "almost-cyclic",
        "formula": "cyclic((2, 3, 5, 8)) with row 3 -> [1, 3, 8, 10] mod 11",
        "pair_cap_ok": true,
        "max_common": 2,
        "indegree_min": 3,
        "indegree_max": 5,
        "odd_cycle": false,
        "rectangle_trap": 0,
        "mutual_phi": 0,
        "forced_classes": [],
        "natural_vertex_circle_obstructed": null,
        "num_filters_passed": 4,
        "survives_all_exact_filters": true,
        "pattern_S": [
          [
            2,
            3,
            5,
            8
          ],
          [
            3,
            4,
            6,
            9
          ],
          [
            4,
            5,
            7,
            10
          ],
          [
            0,
            2,
            4,
            6
          ],
          [
            1,
            6,
            7,
            9
          ],
          [
            2,
            7,
            8,
            10
          ],
          [
            0,
            3,
            8,
            9
          ],
          [
            1,
            4,
            9,
            10
          ],
          [
            0,
            2,
            5,
            10
          ],
          [
            0,
            1,
            3,
            6
          ],
          [
            1,
            2,
            4,
            7
          ]
        ]
      },
      "numeric": {
        "loss": 31.13861242556909,
        "eq_rms": 0.8412465375529056,
        "max_spread": 2.9601655289523143,
        "max_rel_spread": 1.9511253037473877,
        "convexity_margin": 9.999999977088579e-05,
        "min_edge_length": 0.0004323246372343146,
        "min_pair_distance": 0.0004323246372343146,
        "cluster_collapse": false,
        "x_best": [
          1.5293134259996133,
          -2.33080124245545,
          1.940434963023554,
          2.4581453837376825,
          1.7146146149059178,
          -4.902143753719229,
          2.5877544370530896,
          -0.1205435961558114,
          2.3134346180233147,
          -3.7551891020803527,
          -1.3903561636917658,
          0.21616383123029215,
          0.07273596447136263,
          0.07284893143775818,
          0.46086915553438995,
          -0.9191124610165222,
          -0.6459195023966622,
          -0.6460869280840904,
          0.30237053424317156,
          0.6209004101450952,
          0.23259044695597453,
          0.23344291191613245
        ],
        "coordinates": [
          [
            0.6892766905582388,
            -1.1769743641570953e-18
          ],
          [
            0.42902284119691925,
            0.5344850942130024
          ],
          [
            0.42388178092469725,
            0.544659084301648
          ],
          [
            -0.0681284042240827,
            1.4988799040186516
          ],
          [
            -0.7902516953497674,
            0.24757702647075633
          ],
          [
            -0.9380507663954977,
            -0.008669247776914054
          ],
          [
            -0.9378925846463502,
            -0.009071594799018628
          ],
          [
            -0.23867313680367402,
            -1.155403985019038
          ],
          [
            0.019320927294619393,
            -1.5782282543815915
          ],
          [
            0.7050885324824148,
            -0.038665587918632
          ],
          [
            0.7064058149624826,
            -0.035562439108863815
          ]
        ]
      }
    },
    {
      "report": {
        "name": "A11_ac_2_3_5_8_r9_2_3_6_8",
        "n": 11,
        "family": "almost-cyclic",
        "formula": "cyclic((2, 3, 5, 8)) with row 9 -> [2, 3, 6, 8] mod 11",
        "pair_cap_ok": true,
        "max_common": 2,
        "indegree_min": 3,
        "indegree_max": 5,
        "odd_cycle": true,
        "rectangle_trap": 0,
        "mutual_phi": 0,
        "forced_classes": [],
        "natural_vertex_circle_obstructed": null,
        "num_filters_passed": 2,
        "survives_all_exact_filters": false,
        "pattern_S": [
          [
            2,
            3,
            5,
            8
          ],
          [
            3,
            4,
            6,
            9
          ],
          [
            4,
            5,
            7,
            10
          ],
          [
            0,
            5,
            6,
            8
          ],
          [
            1,
            6,
            7,
            9
          ],
          [
            2,
            7,
            8,
            10
          ],
          [
            0,
            3,
            8,
            9
          ],
          [
            1,
            4,
            9,
            10
          ],
          [
            0,
            2,
            5,
            10
          ],
          [
            0,
            1,
            4,
            6
          ],
          [
            1,
            2,
            4,
            7
          ]
        ]
      },
      "numeric": null
    },
    {
      "report": {
        "name": "A11_ac_2_3_5_8_r5_2_5_6_7",
        "n": 11,
        "family": "almost-cyclic",
        "formula": "cyclic((2, 3, 5, 8)) with row 5 -> [2, 5, 6, 7] mod 11",
        "pair_cap_ok": true,
        "max_common": 2,
        "indegree_min": 3,
        "indegree_max": 5,
        "odd_cycle": false,
        "rectangle_trap": 0,
        "mutual_phi": 0,
        "forced_classes": [],
        "natural_vertex_circle_obstructed": null,
        "num_filters_passed": 3,
        "survives_all_exact_filters": false,
        "pattern_S": [
          [
            2,
            3,
            5,
            8
          ],
          [
            3,
            4,
            6,
            9
          ],
          [
            4,
            5,
            7,
            10
          ],
          [
            0,
            5,
            6,
            8
          ],
          [
            1,
            6,
            7,
            9
          ],
          [
            0,
            1,
            7,
            10
          ],
          [
            0,
            3,
            8,
            9
          ],
          [
            1,
            4,
            9,
            10
          ],
          [
            0,
            2,
            5,
            10
          ],
          [
            0,
            1,
            3,
            6
          ],
          [
            1,
            2,
            4,
            7
          ]
        ]
      },
      "numeric": null
    },
    {
      "report": {
        "name": "A11_ac_2_3_5_8_r8_2_3_4_5",
        "n": 11,
        "family": "almost-cyclic",
        "formula": "cyclic((2, 3, 5, 8)) with row 8 -> [2, 3, 4, 5] mod 11",
        "pair_cap_ok": true,
        "max_common": 2,
        "indegree_min": 3,
        "indegree_max": 5,
        "odd_cycle": false,
        "rectangle_trap": 0,
        "mutual_phi": 0,
        "forced_classes": [],
        "natural_vertex_circle_obstructed": null,
        "num_filters_passed": 3,
        "survives_all_exact_filters": false,
        "pattern_S": [
          [
            2,
            3,
            5,
            8
          ],
          [
            3,
            4,
            6,
            9
          ],
          [
            4,
            5,
            7,
            10
          ],
          [
            0,
            5,
            6,
            8
          ],
          [
            1,
            6,
            7,
            9
          ],
          [
            2,
            7,
            8,
            10
          ],
          [
            0,
            3,
            8,
            9
          ],
          [
            1,
            4,
            9,
            10
          ],
          [
            0,
            1,
            2,
            10
          ],
          [
            0,
            1,
            3,
            6
          ],
          [
            1,
            2,
            4,
            7
          ]
        ]
      },
      "numeric": null
    },
    {
      "report": {
        "name": "A11_ac_2_3_5_8_r0_1_3_5_8",
        "n": 11,
        "family": "almost-cyclic",
        "formula": "cyclic((2, 3, 5, 8)) with row 0 -> [1, 3, 5, 8] mod 11",
        "pair_cap_ok": true,
        "max_common": 2,
        "indegree_min": 3,
        "indegree_max": 5,
        "odd_cycle": false,
        "rectangle_trap": 0,
        "mutual_phi": 0,
        "forced_classes": [],
        "natural_vertex_circle_obstructed": null,
        "num_filters_passed": 4,
        "survives_all_exact_filters": true,
        "pattern_S": [
          [
            1,
            3,
            5,
            8
          ],
          [
            3,
            4,
            6,
            9
          ],
          [
            4,
            5,
            7,
            10
          ],
          [
            0,
            5,
            6,
            8
          ],
          [
            1,
            6,
            7,
            9
          ],
          [
            2,
            7,
            8,
            10
          ],
          [
            0,
            3,
            8,
            9
          ],
          [
            1,
            4,
            9,
            10
          ],
          [
            0,
            2,
            5,
            10
          ],
          [
            0,
            1,
            3,
            6
          ],
          [
            1,
            2,
            4,
            7
          ]
        ]
      },
      "numeric": {
        "loss": 38.593753467029295,
        "eq_rms": 0.9365525936189072,
        "max_spread": 2.900310205473598,
        "max_rel_spread": 1.6208063921107518,
        "convexity_margin": 9.999999982188146e-05,
        "min_edge_length": 0.03991581048336551,
        "min_pair_distance": 0.03991581048336551,
        "cluster_collapse": false,
        "x_best": [
          0.06320125498962482,
          -1.7905014491767965,
          1.8401701130815027,
          -0.9605785530872871,
          0.9729258834617929,
          0.16829119825872543,
          -1.5074205164680745,
          1.1788399779812726,
          -0.6572189502472331,
          -0.7375268925388798,
          1.4913915973304674,
          -0.5134158706225659,
          -0.3887306065653637,
          -0.35830864965589504,
          -0.2082417103094998,
          -0.07185691846518649,
          0.01466704476549835,
          0.31320456224676996,
          0.39747509078262705,
          0.20523052765978284,
          0.27150163597509347,
          0.36023852599284656
        ],
        "coordinates": [
          [
            0.8773269907712191,
            -2.926503047367069e-17
          ],
          [
            0.994508212570331,
            0.1813484314766961
          ],
          [
            1.0157809665578577,
            0.21512330178481304
          ],
          [
            0.05953826376723711,
            0.9610008936802246
          ],
          [
            -0.07759271263338854,
            1.0283574397875745
          ],
          [
            -0.6185864371463256,
            0.5082166874221183
          ],
          [
            -1.007038981954542,
            0.13455246590705827
          ],
          [
            -1.1156291793787965,
            0.029838847400702494
          ],
          [
            -0.19875415461048582,
            -0.8672001687076123
          ],
          [
            -0.04678350353815716,
            -1.0157739651743176
          ],
          [
            0.11723053559505091,
            -1.1754639335772576
          ]
        ]
      }
    },
    {
      "report": {
        "name": "A11_ac_2_3_5_8_r9_1_2_3_10",
        "n": 11,
        "family": "almost-cyclic",
        "formula": "cyclic((2, 3, 5, 8)) with row 9 -> [1, 2, 3, 10] mod 11",
        "pair_cap_ok": true,
        "max_common": 2,
        "indegree_min": 3,
        "indegree_max": 5,
        "odd_cycle": true,
        "rectangle_trap": 0,
        "mutual_phi": 0,
        "forced_classes": [],
        "natural_vertex_circle_obstructed": null,
        "num_filters_passed": 2,
        "survives_all_exact_filters": false,
        "pattern_S": [
          [
            2,
            3,
            5,
            8
          ],
          [
            3,
            4,
            6,
            9
          ],
          [
            4,
            5,
            7,
            10
          ],
          [
            0,
            5,
            6,
            8
          ],
          [
            1,
            6,
            7,
            9
          ],
          [
            2,
            7,
            8,
            10
          ],
          [
            0,
            3,
            8,
            9
          ],
          [
            1,
            4,
            9,
            10
          ],
          [
            0,
            2,
            5,
            10
          ],
          [
            0,
            1,
            8,
            10
          ],
          [
            1,
            2,
            4,
            7
          ]
        ]
      },
      "numeric": null
    },
    {
      "report": {
        "name": "A11_ac_2_3_5_8_r7_4_6_8_10",
        "n": 11,
        "family": "almost-cyclic",
        "formula": "cyclic((2, 3, 5, 8)) with row 7 -> [4, 6, 8, 10] mod 11",
        "pair_cap_ok": true,
        "max_common": 2,
        "indegree_min": 3,
        "indegree_max": 5,
        "odd_cycle": false,
        "rectangle_trap": 0,
        "mutual_phi": 0,
        "forced_classes": [],
        "natural_vertex_circle_obstructed": null,
        "num_filters_passed": 3,
        "survives_all_exact_filters": false,
        "pattern_S": [
          [
            2,
            3,
            5,
            8
          ],
          [
            3,
            4,
            6,
            9
          ],
          [
            4,
            5,
            7,
            10
          ],
          [
            0,
            5,
            6,
            8
          ],
          [
            1,
            6,
            7,
            9
          ],
          [
            2,
            7,
            8,
            10
          ],
          [
            0,
            3,
            8,
            9
          ],
          [
            0,
            2,
            4,
            6
          ],
          [
            0,
            2,
            5,
            10
          ],
          [
            0,
            1,
            3,
            6
          ],
          [
            1,
            2,
            4,
            7
          ]
        ]
      },
      "numeric": null
    },
    {
      "report": {
        "name": "A11_ac_2_3_5_8_r1_2_3_5_6",
        "n": 11,
        "family": "almost-cyclic",
        "formula": "cyclic((2, 3, 5, 8)) with row 1 -> [2, 3, 5, 6] mod 11",
        "pair_cap_ok": true,
        "max_common": 2,
        "indegree_min": 3,
        "indegree_max": 5,
        "odd_cycle": false,
        "rectangle_trap": 0,
        "mutual_phi": 0,
        "forced_classes": [],
        "natural_vertex_circle_obstructed": null,
        "num_filters_passed": 3,
        "survives_all_exact_filters": false,
        "pattern_S": [
          [
            2,
            3,
            5,
            8
          ],
          [
            3,
            4,
            6,
            7
          ],
          [
            4,
            5,
            7,
            10
          ],
          [
            0,
            5,
            6,
            8
          ],
          [
            1,
            6,
            7,
            9
          ],
          [
            2,
            7,
            8,
            10
          ],
          [
            0,
            3,
            8,
            9
          ],
          [
            1,
            4,
            9,
            10
          ],
          [
            0,
            2,
            5,
            10
          ],
          [
            0,
            1,
            3,
            6
          ],
          [
            1,
            2,
            4,
            7
          ]
        ]
      },
      "numeric": null
    },
    {
      "report": {
        "name": "A11_ac_2_3_5_8_r8_2_3_4_8",
        "n": 11,
        "family": "almost-cyclic",
        "formula": "cyclic((2, 3, 5, 8)) with row 8 -> [2, 3, 4, 8] mod 11",
        "pair_cap_ok": true,
        "max_common": 2,
        "indegree_min": 3,
        "indegree_max": 5,
        "odd_cycle": true,
        "rectangle_trap": 0,
        "mutual_phi": 0,
        "forced_classes": [],
        "natural_vertex_circle_obstructed": null,
        "num_filters_passed": 2,
        "survives_all_exact_filters": false,
        "pattern_S": [
          [
            2,
            3,
            5,
            8
          ],
          [
            3,
            4,
            6,
            9
          ],
          [
            4,
            5,
            7,
            10
          ],
          [
            0,
            5,
            6,
            8
          ],
          [
            1,
            6,
            7,
            9
          ],
          [
            2,
            7,
            8,
            10
          ],
          [
            0,
            3,
            8,
            9
          ],
          [
            1,
            4,
            9,
            10
          ],
          [
            0,
            1,
            5,
            10
          ],
          [
            0,
            1,
            3,
            6
          ],
          [
            1,
            2,
            4,
            7
          ]
        ]
      },
      "numeric": null
    },
    {
      "report": {
        "name": "A11_ac_2_3_5_8_r0_1_2_3_9",
        "n": 11,
        "family": "almost-cyclic",
        "formula": "cyclic((2, 3, 5, 8)) with row 0 -> [1, 2, 3, 9] mod 11",
        "pair_cap_ok": true,
        "max_common": 2,
        "indegree_min": 3,
        "indegree_max": 5,
        "odd_cycle": false,
        "rectangle_trap": 0,
        "mutual_phi": 1,
        "forced_classes": [],
        "natural_vertex_circle_obstructed": null,
        "num_filters_passed": 3,
        "survives_all_exact_filters": false,
        "pattern_S": [
          [
            1,
            2,
            3,
            9
          ],
          [
            3,
            4,
            6,
            9
          ],
          [
            4,
            5,
            7,
            10
          ],
          [
            0,
            5,
            6,
            8
          ],
          [
            1,
            6,
            7,
            9
          ],
          [
            2,
            7,
            8,
            10
          ],
          [
            0,
            3,
            8,
            9
          ],
          [
            1,
            4,
            9,
            10
          ],
          [
            0,
            2,
            5,
            10
          ],
          [
            0,
            1,
            3,
            6
          ],
          [
            1,
            2,
            4,
            7
          ]
        ]
      },
      "numeric": null
    },
    {
      "report": {
        "name": "A11_ac_2_3_5_8_r6_1_2_5_9",
        "n": 11,
        "family": "almost-cyclic",
        "formula": "cyclic((2, 3, 5, 8)) with row 6 -> [1, 2, 5, 9] mod 11",
        "pair_cap_ok": true,
        "max_common": 2,
        "indegree_min": 3,
        "indegree_max": 5,
        "odd_cycle": false,
        "rectangle_trap": 0,
        "mutual_phi": 0,
        "forced_classes": [],
        "natural_vertex_circle_obstructed": null,
        "num_filters_passed": 3,
        "survives_all_exact_filters": false,
        "pattern_S": [
          [
            2,
            3,
            5,
            8
          ],
          [
            3,
            4,
            6,
            9
          ],
          [
            4,
            5,
            7,
            10
          ],
          [
            0,
            5,
            6,
            8
          ],
          [
            1,
            6,
            7,
            9
          ],
          [
            2,
            7,
            8,
            10
          ],
          [
            0,
            4,
            7,
            8
          ],
          [
            1,
            4,
            9,
            10
          ],
          [
            0,
            2,
            5,
            10
          ],
          [
            0,
            1,
            3,
            6
          ],
          [
            1,
            2,
            4,
            7
          ]
        ]
      },
      "numeric": null
    },
    {
      "report": {
        "name": "A11_ac_2_3_5_8_r3_3_6_7_10",
        "n": 11,
        "family": "almost-cyclic",
        "formula": "cyclic((2, 3, 5, 8)) with row 3 -> [3, 6, 7, 10] mod 11",
        "pair_cap_ok": true,
        "max_common": 2,
        "indegree_min": 3,
        "indegree_max": 5,
        "odd_cycle": false,
        "rectangle_trap": 0,
        "mutual_phi": 0,
        "forced_classes": [],
        "natural_vertex_circle_obstructed": null,
        "num_filters_passed": 3,
        "survives_all_exact_filters": false,
        "pattern_S": [
          [
            2,
            3,
            5,
            8
          ],
          [
            3,
            4,
            6,
            9
          ],
          [
            4,
            5,
            7,
            10
          ],
          [
            2,
            6,
            9,
            10
          ],
          [
            1,
            6,
            7,
            9
          ],
          [
            2,
            7,
            8,
            10
          ],
          [
            0,
            3,
            8,
            9
          ],
          [
            1,
            4,
            9,
            10
          ],
          [
            0,
            2,
            5,
            10
          ],
          [
            0,
            1,
            3,
            6
          ],
          [
            1,
            2,
            4,
            7
          ]
        ]
      },
      "numeric": null
    },
    {
      "report": {
        "name": "A11_ac_2_3_5_8_r1_3_6_8_10",
        "n": 11,
        "family": "almost-cyclic",
        "formula": "cyclic((2, 3, 5, 8)) with row 1 -> [3, 6, 8, 10] mod 11",
        "pair_cap_ok": true,
        "max_common": 2,
        "indegree_min": 3,
        "indegree_max": 5,
        "odd_cycle": false,
        "rectangle_trap": 0,
        "mutual_phi": 0,
        "forced_classes": [],
        "natural_vertex_circle_obstructed": null,
        "num_filters_passed": 3,
        "survives_all_exact_filters": false,
        "pattern_S": [
          [
            2,
            3,
            5,
            8
          ],
          [
            0,
            4,
            7,
            9
          ],
          [
            4,
            5,
            7,
            10
          ],
          [
            0,
            5,
            6,
            8
          ],
          [
            1,
            6,
            7,
            9
          ],
          [
            2,
            7,
            8,
            10
          ],
          [
            0,
            3,
            8,
            9
          ],
          [
            1,
            4,
            9,
            10
          ],
          [
            0,
            2,
            5,
            10
          ],
          [
            0,
            1,
            3,
            6
          ],
          [
            1,
            2,
            4,
            7
          ]
        ]
      },
      "numeric": null
    },
    {
      "report": {
        "name": "A11_ac_2_3_5_8_r9_2_4_6_10",
        "n": 11,
        "family": "almost-cyclic",
        "formula": "cyclic((2, 3, 5, 8)) with row 9 -> [2, 4, 6, 10] mod 11",
        "pair_cap_ok": true,
        "max_common": 2,
        "indegree_min": 3,
        "indegree_max": 5,
        "odd_cycle": true,
        "rectangle_trap": 0,
        "mutual_phi": 0,
        "forced_classes": [],
        "natural_vertex_circle_obstructed": null,
        "num_filters_passed": 2,
        "survives_all_exact_filters": false,
        "pattern_S": [
          [
            2,
            3,
            5,
            8
          ],
          [
            3,
            4,
            6,
            9
          ],
          [
            4,
            5,
            7,
            10
          ],
          [
            0,
            5,
            6,
            8
          ],
          [
            1,
            6,
            7,
            9
          ],
          [
            2,
            7,
            8,
            10
          ],
          [
            0,
            3,
            8,
            9
          ],
          [
            1,
            4,
            9,
            10
          ],
          [
            0,
            2,
            5,
            10
          ],
          [
            0,
            2,
            4,
            8
          ],
          [
            1,
            2,
            4,
            7
          ]
        ]
      },
      "numeric": null
    },
    {
      "report": {
        "name": "A11_ac_2_3_5_8_r8_1_5_8_9",
        "n": 11,
        "family": "almost-cyclic",
        "formula": "cyclic((2, 3, 5, 8)) with row 8 -> [1, 5, 8, 9] mod 11",
        "pair_cap_ok": true,
        "max_common": 2,
        "indegree_min": 3,
        "indegree_max": 5,
        "odd_cycle": false,
        "rectangle_trap": 0,
        "mutual_phi": 0,
        "forced_classes": [],
        "natural_vertex_circle_obstructed": null,
        "num_filters_passed": 4,
        "survives_all_exact_filters": true,
        "pattern_S": [
          [
            2,
            3,
            5,
            8
          ],
          [
            3,
            4,
            6,
            9
          ],
          [
            4,
            5,
            7,
            10
          ],
          [
            0,
            5,
            6,
            8
          ],
          [
            1,
            6,
            7,
            9
          ],
          [
            2,
            7,
            8,
            10
          ],
          [
            0,
            3,
            8,
            9
          ],
          [
            1,
            4,
            9,
            10
          ],
          [
            2,
            5,
            6,
            9
          ],
          [
            0,
            1,
            3,
            6
          ],
          [
            1,
            2,
            4,
            7
          ]
        ]
      },
      "numeric": {
        "loss": 38.171873338329526,
        "eq_rms": 0.9314196561545851,
        "max_spread": 2.9488082558390993,
        "max_rel_spread": 1.575461184229617,
        "convexity_margin": 9.999999989752017e-05,
        "min_edge_length": 0.07947588884337022,
        "min_pair_distance": 0.07947588884337022,
        "cluster_collapse": false,
        "x_best": [
          1.0059159075057698,
          -0.5350090891018656,
          -0.18389932587729743,
          0.9573318158962442,
          0.7362961398625232,
          -1.3212008799759527,
          -0.04234245380082353,
          1.225847116054742,
          -1.6353823565423424,
          -0.9504482167867049,
          0.8046813526034201,
          0.07953479563153268,
          -0.2331198880535755,
          -0.14267225557937205,
          0.10524873741980252,
          0.018930117213770442,
          -0.041700959770737435,
          -0.0003551179991015582,
          0.26597071798453314,
          -0.069169373027202,
          -0.029885627896352768,
          0.06944284104162522
        ],
        "coordinates": [
          [
            1.1010761536532478,
            9.573948198407013e-18
          ],
          [
            0.4659579256961904,
            0.7219335097186861
          ],
          [
            0.33494507985608923,
            0.8706972507931247
          ],
          [
            0.07594039176060366,
            1.1640311304632958
          ],
          [
            -0.7904939308327812,
            0.6390053489375926
          ],
          [
            -0.8886320355975831,
            -0.1201265054773075
          ],
          [
            -0.9022093764641632,
            -0.22617085975756732
          ],
          [
            -0.9661900606434844,
            -0.7332502951110712
          ],
          [
            0.41028654665258907,
            -0.7695822686477967
          ],
          [
            0.48973664794395744,
            -0.7716066975141793
          ],
          [
            0.6695826579753348,
            -0.7749306134047775
          ]
        ]
      }
    },
    {
      "report": {
        "name": "A11_ac_2_3_5_8_r3_1_3_4_8",
        "n": 11,
        "family": "almost-cyclic",
        "formula": "cyclic((2, 3, 5, 8)) with row 3 -> [1, 3, 4, 8] mod 11",
        "pair_cap_ok": true,
        "max_common": 2,
        "indegree_min": 3,
        "indegree_max": 5,
        "odd_cycle": false,
        "rectangle_trap": 0,
        "mutual_phi": 0,
        "forced_classes": [],
        "natural_vertex_circle_obstructed": null,
        "num_filters_passed": 3,
        "survives_all_exact_filters": false,
        "pattern_S": [
          [
            2,
            3,
            5,
            8
          ],
          [
            3,
            4,
            6,
            9
          ],
          [
            4,
            5,
            7,
            10
          ],
          [
            0,
            4,
            6,
            7
          ],
          [
            1,
            6,
            7,
            9
          ],
          [
            2,
            7,
            8,
            10
          ],
          [
            0,
            3,
            8,
            9
          ],
          [
            1,
            4,
            9,
            10
          ],
          [
            0,
            2,
            5,
            10
          ],
          [
            0,
            1,
            3,
            6
          ],
          [
            1,
            2,
            4,
            7
          ]
        ]
      },
      "numeric": null
    },
    {
      "report": {
        "name": "A11_ac_2_3_5_8_r0_2_3_5_7",
        "n": 11,
        "family": "almost-cyclic",
        "formula": "cyclic((2, 3, 5, 8)) with row 0 -> [2, 3, 5, 7] mod 11",
        "pair_cap_ok": true,
        "max_common": 2,
        "indegree_min": 3,
        "indegree_max": 5,
        "odd_cycle": false,
        "rectangle_trap": 0,
        "mutual_phi": 0,
        "forced_classes": [],
        "natural_vertex_circle_obstructed": null,
        "num_filters_passed": 3,
        "survives_all_exact_filters": false,
        "pattern_S": [
          [
            2,
            3,
            5,
            7
          ],
          [
            3,
            4,
            6,
            9
          ],
          [
            4,
            5,
            7,
            10
          ],
          [
            0,
            5,
            6,
            8
          ],
          [
            1,
            6,
            7,
            9
          ],
          [
            2,
            7,
            8,
            10
          ],
          [
            0,
            3,
            8,
            9
          ],
          [
            1,
            4,
            9,
            10
          ],
          [
            0,
            2,
            5,
            10
          ],
          [
            0,
            1,
            3,
            6
          ],
          [
            1,
            2,
            4,
            7
          ]
        ]
      },
      "numeric": null
    }
  ]
}